<?xml version="1.0" encoding="UTF-8" standalone="yes"?>
<p:sld xmlns:a="http://schemas.openxmlformats.org/drawingml/2006/main" xmlns:r="http://schemas.openxmlformats.org/officeDocument/2006/relationships" xmlns:p="http://schemas.openxmlformats.org/presentationml/2006/main"><p:cSld><p:spTree><p:nvGrpSpPr><p:cNvPr id="1" name=""/><p:cNvGrpSpPr/><p:nvPr/></p:nvGrpSpPr><p:grpSpPr><a:xfrm><a:off x="0" y="0"/><a:ext cx="0" cy="0"/><a:chOff x="0" y="0"/><a:chExt cx="0" cy="0"/></a:xfrm></p:grpSpPr><p:sp><p:nvSpPr><p:cNvPr id="5" name="Subtitle 2"><a:extLst><a:ext uri="{FF2B5EF4-FFF2-40B4-BE49-F238E27FC236}"><a16:creationId xmlns:a16="http://schemas.microsoft.com/office/drawing/2014/main" id="{7D5CECEB-FC46-B1DC-97D5-66DC40343705}"/></a:ext></a:extLst></p:cNvPr><p:cNvSpPr><a:spLocks noGrp="1"/></p:cNvSpPr><p:nvPr><p:ph type="subTitle" idx="1"/></p:nvPr></p:nvSpPr><p:spPr><a:xfrm><a:off x="762643" y="4976829"/><a:ext cx="4333464" cy="567875"/></a:xfrm></p:spPr><p:txBody><a:bodyPr><a:normAutofit fontScale="92500" lnSpcReduction="10000"/></a:bodyPr><a:lstStyle/><a:p><a:pPr><a:lnSpc><a:spcPct val="110000"/></a:lnSpc></a:pPr><a:r><a:rPr lang="en-US" err="1"/><a:t>Subheader</a:t></a:r><a:r><a:rPr lang="en-US"/><a:t> goes here</a:t></a:r><a:br><a:rPr lang="en-US"/></a:br><a:r><a:rPr lang="en-US"/><a:t>Lorem Ipsum Dolor Sit </a:t></a:r><a:r><a:rPr lang="en-US" err="1"/><a:t>Amet</a:t></a:r><a:r><a:rPr lang="en-US"/><a:t> Lorem</a:t></a:r></a:p></p:txBody></p:sp><p:sp><p:nvSpPr><p:cNvPr id="6" name="Text Placeholder 3"><a:extLst><a:ext uri="{FF2B5EF4-FFF2-40B4-BE49-F238E27FC236}"><a16:creationId xmlns:a16="http://schemas.microsoft.com/office/drawing/2014/main" id="{36FC4012-923D-74D3-B048-504CEF608642}"/></a:ext></a:extLst></p:cNvPr><p:cNvSpPr><a:spLocks noGrp="1"/></p:cNvSpPr><p:nvPr><p:ph type="body" sz="quarter" idx="10"/></p:nvPr></p:nvSpPr><p:spPr><a:xfrm><a:off x="762000" y="5917152"/><a:ext cx="3509962" cy="346075"/></a:xfrm></p:spPr><p:txBody><a:bodyPr/><a:lstStyle/><a:p><a:r><a:rPr lang="en-US"/><a:t>APRIL 2, 2025</a:t></a:r></a:p></p:txBody></p:sp><p:sp><p:nvSpPr><p:cNvPr id="7" name="Rectangle 6"><a:extLst><a:ext uri="{FF2B5EF4-FFF2-40B4-BE49-F238E27FC236}"><a16:creationId xmlns:a16="http://schemas.microsoft.com/office/drawing/2014/main" id="{77865552-4256-E7AE-1629-EEB38DEED2F5}"/></a:ext></a:extLst></p:cNvPr><p:cNvSpPr/><p:nvPr/></p:nvSpPr><p:spPr><a:xfrm><a:off x="636104" y="2946399"/><a:ext cx="4333464" cy="919600"/></a:xfrm><a:prstGeom prst="rect"><a:avLst/></a:prstGeom><a:solidFill><a:srgbClr val="DAF49D"/></a:solidFill><a:ln><a:noFill/></a:ln></p:spPr><p:style><a:lnRef idx="2"><a:schemeClr val="accent1"><a:shade val="15000"/></a:schemeClr></a:lnRef><a:fillRef idx="1"><a:schemeClr val="accent1"/></a:fillRef><a:effectRef idx="0"><a:schemeClr val="accent1"/></a:effectRef><a:fontRef idx="minor"><a:schemeClr val="lt1"/></a:fontRef></p:style><p:txBody><a:bodyPr rtlCol="0" anchor="ctr"/><a:lstStyle/><a:p><a:pPr algn="ctr"/><a:endParaRPr lang="en-US"/></a:p></p:txBody></p:sp><p:sp><p:nvSpPr><p:cNvPr id="8" name="Title 1"><a:extLst><a:ext uri="{FF2B5EF4-FFF2-40B4-BE49-F238E27FC236}"><a16:creationId xmlns:a16="http://schemas.microsoft.com/office/drawing/2014/main" id="{27EF1FE6-281F-C49D-D70C-931806A1E3C8}"/></a:ext></a:extLst></p:cNvPr><p:cNvSpPr><a:spLocks noGrp="1"/></p:cNvSpPr><p:nvPr><p:ph type="ctrTitle"/></p:nvPr></p:nvSpPr><p:spPr><a:xfrm><a:off x="762000" y="1849102"/><a:ext cx="5003800" cy="2957220"/></a:xfrm></p:spPr><p:txBody><a:bodyPr/><a:lstStyle/><a:p><a:r><a:rPr lang="en-US"/><a:t>Title Goes Here Lorem Ipsum Sit</a:t></a:r></a:p></p:txBody></p:sp><p:cxnSp><p:nvCxnSpPr><p:cNvPr id="19" name="Straight Connector 18"><a:extLst><a:ext uri="{FF2B5EF4-FFF2-40B4-BE49-F238E27FC236}"><a16:creationId xmlns:a16="http://schemas.microsoft.com/office/drawing/2014/main" id="{1E8C8232-E36E-F31A-90C1-274A62252233}"/></a:ext></a:extLst></p:cNvPr><p:cNvCxnSpPr><a:cxnSpLocks/></p:cNvCxnSpPr><p:nvPr/></p:nvCxnSpPr><p:spPr><a:xfrm flipH="1"><a:off x="762000" y="5723069"/><a:ext cx="4311805" cy="0"/></a:xfrm><a:prstGeom prst="line"><a:avLst/></a:prstGeom><a:ln w="6350"><a:solidFill><a:schemeClr val="tx2"/></a:solidFill></a:ln></p:spPr><p:style><a:lnRef idx="2"><a:schemeClr val="accent1"/></a:lnRef><a:fillRef idx="0"><a:schemeClr val="accent1"/></a:fillRef><a:effectRef idx="1"><a:schemeClr val="accent1"/></a:effectRef><a:fontRef idx="minor"><a:schemeClr val="tx1"/></a:fontRef></p:style></p:cxnSp></p:spTree><p:extLst><p:ext uri="{BB962C8B-B14F-4D97-AF65-F5344CB8AC3E}"><p14:creationId xmlns:p14="http://schemas.microsoft.com/office/powerpoint/2010/main" val="2902409128"/></p:ext></p:extLst></p:cSld><p:clrMapOvr><a:masterClrMapping/></p:clrMapOvr></p:sld>